infomark_platform/__init__.py
infomark_platform/base_helpers.py
infomark_platform/config_terminal.py
infomark_platform/custom_prompt_toolkit.py
infomark_platform/decorators.py
infomark_platform/featflags_controller.py
infomark_platform/helper_classes.py
infomark_platform/helper_denomination.py
infomark_platform/helper_funcs.py
infomark_platform/keys_controller.py
infomark_platform/keys_model.py
infomark_platform/keys_view.py
infomark_platform/loggers.py
infomark_platform/menu.py
infomark_platform/parent_classes.py
infomark_platform/rich_config.py
infomark_platform/routine_functions.py
infomark_platform/sdk.py
infomark_platform/settings_controller.py
infomark_platform/sources_controller.py
infomark_platform/terminal_controller.py
infomark_platform/terminal_helper.py
infomark_platform/thought_of_the_day.py
infomark_platform/account/__init__.py
infomark_platform/account/account_controller.py
infomark_platform/account/account_view.py
infomark_platform/account/show_prompt.py
infomark_platform/alternative/__init__.py
infomark_platform/alternative/alt_controller.py
infomark_platform/alternative/hackernews_model.py
infomark_platform/alternative/hackernews_view.py
infomark_platform/alternative/realestate/__init__.py
infomark_platform/alternative/realestate/landRegistry_model.py
infomark_platform/alternative/realestate/landRegistry_view.py
infomark_platform/alternative/realestate/realestate_controller.py
infomark_platform/common/__init__.py
infomark_platform/common/biztoc_model.py
infomark_platform/common/biztoc_view.py
infomark_platform/common/common_model.py
infomark_platform/common/feedparser_model.py
infomark_platform/common/feedparser_view.py
infomark_platform/common/news_sdk_helper.py
infomark_platform/common/newsapi_model.py
infomark_platform/common/newsapi_view.py
infomark_platform/common/behavioural_analysis/__init__.py
infomark_platform/common/behavioural_analysis/finbrain_model.py
infomark_platform/common/behavioural_analysis/finbrain_view.py
infomark_terminal-1.0.0.dist-info/METADATA
infomark_terminal-1.0.0.dist-info/WHEEL
infomark_terminal-1.0.0.dist-info/entry_points.txt
infomark_terminal-1.0.0.dist-info/top_level.txt
infomark_terminal-1.0.0.dist-info/RECORD
